LICENSE
MANIFEST.in
NOTICE
setup.cfg
setup.py
chalice_view/__init__.py
chalice_view/app.py
chalice_view/cli.py
chalice_view/config.py
chalice_view/exceptions.py
chalice_view/manager.py
chalice_view/router.py
chalice_view/routes.py
chalice_view/test.py
chalice_view/utils.py
chalice_view/view.py
chalice_view/views.py
chalice_view.egg-info/PKG-INFO
chalice_view.egg-info/SOURCES.txt
chalice_view.egg-info/dependency_links.txt
chalice_view.egg-info/not-zip-safe
chalice_view.egg-info/requires.txt
chalice_view.egg-info/top_level.txt